rtl2/counter.sv
// Synchronous Up/Down Counter
// 4-bit, with load, enable, and overflow detection
// Author: Sindhu Govindareddy Doddamane

module counter #(
  parameter WIDTH = 4
)(
  input  logic             clk,
  input  logic             rst_n,
  input  logic             enable,
  input  logic             up_down,  // 1=up, 0=down
  input  logic             load,
  input  logic [WIDTH-1:0] load_val,
  output logic [WIDTH-1:0] count,
  output logic             overflow,
  output logic             underflow
);

  always_ff @(posedge clk or negedge rst_n) begin
    if (!rst_n) begin
      count <= 0;
    end else if (load) begin
      count <= load_val;
    end else if (enable) begin
      if (up_down)
        count <= count + 1;
      else
        count <= count - 1;
    end
  end

  assign overflow  = (count == 4'hF) && enable && up_down;
  assign underflow = (count == 4'h0) && enable && !up_down;

endmodule

tb2/counter_tb.sv
// Counter Testbench
// Author: Sindhu Govindareddy Doddamane

`timescale 1ns/1ps

module counter_tb;

  parameter WIDTH = 4;

  logic             clk;
  logic             rst_n;
  logic             enable;
  logic             up_down;
  logic             load;
  logic [WIDTH-1:0] load_val;
  logic [WIDTH-1:0] count;
  logic             overflow;
  logic             underflow;

  // Instantiate DUT
  counter #(.WIDTH(WIDTH)) dut (
    .clk      (clk),
    .rst_n    (rst_n),
    .enable   (enable),
    .up_down  (up_down),
    .load     (load),
    .load_val (load_val),
    .count    (count),
    .overflow (overflow),
    .underflow(underflow)
  );

  // Clock
  initial clk = 0;
  always #5 clk = ~clk;

  // Coverage tracking
  integer cov_up_seen       = 0;
  integer cov_down_seen     = 0;
  integer cov_overflow_seen = 0;
  integer cov_load_seen     = 0;

  always @(posedge clk) begin
    if (up_down && enable) cov_up_seen       = 1;
    if (!up_down && enable) cov_down_seen    = 1;
    if (overflow)           cov_overflow_seen = 1;
    if (load)               cov_load_seen     = 1;
  end

  integer pass_count = 0;
  integer fail_count = 0;

  initial begin
    // Init
    rst_n = 0; enable = 0; up_down = 1;
    load = 0; load_val = 0;
    repeat(2) @(posedge clk);
    rst_n = 1;

    // Test 1: Count Up
    $display("\n--- Test 1: Count Up ---");
    enable = 1; up_down = 1;
    repeat(5) @(posedge clk);
    enable = 0;
    if (count == 5) begin
      $display("PASS: Count up to 5 correctly"); pass_count++;
    end else begin
      $display("FAIL: Count up failed, got %0d", count); fail_count++;
    end

    // Test 2: Count Down
    $display("\n--- Test 2: Count Down ---");
    enable = 1; up_down = 0;
    repeat(3) @(posedge clk);
    enable = 0;
    if (count == 2) begin
      $display("PASS: Count down to 2 correctly"); pass_count++;
    end else begin
      $display("FAIL: Count down failed, got %0d", count); fail_count++;
    end

    // Test 3: Load Value
    $display("\n--- Test 3: Load Value ---");
    load = 1; load_val = 4'hA;
    @(posedge clk);
    load = 0;
    if (count == 4'hA) begin
      $display("PASS: Load value 10 correctly"); pass_count++;
    end else begin
      $display("FAIL: Load failed, got %0d", count); fail_count++;
    end

    // Test 4: Overflow Detection
    $display("\n--- Test 4: Overflow Detection ---");
    load = 1; load_val = 4'hE;
    @(posedge clk);
    load = 0;
    enable = 1; up_down = 1;
    @(posedge clk);
    if (overflow) begin
      $display("PASS: Overflow detected correctly"); pass_count++;
    end else begin
      $display("FAIL: Overflow not detected"); fail_count++;
    end
    enable = 0;

    // Test 5: Reset
    $display("\n--- Test 5: Reset ---");
    rst_n = 0;
    @(posedge clk);
    rst_n = 1;
    if (count == 0) begin
      $display("PASS: Reset works correctly"); pass_count++;
    end else begin
      $display("FAIL: Reset failed, got %0d", count); fail_count++;
    end

    // Summary
    $display("\n================================");
    $display("  TEST SUMMARY");
    $display("  PASSED : %0d", pass_count);
    $display("  FAILED : %0d", fail_count);
    $display("================================\n");

    // Coverage
    begin
      integer cov_total;
      cov_total = cov_up_seen + cov_down_seen +
                  cov_overflow_seen + cov_load_seen;
      $display("Functional Coverage: %0.2f%%",
               (cov_total / 4.0) * 100.0);
    end

    $finish;
  end

  initial begin
    $dumpfile("sim/counter_tb.vcd");
    $dumpvars(0, counter_tb);
  end

endmodule

sim/counter_tb.vcd
$date
	Wed May  6 16:55:08 2026
$end
$version
	Icarus Verilog
$end
$timescale
	1ps
$end
$scope module counter_tb $end
$var wire 1 ! underflow $end
$var wire 1 " overflow $end
$var wire 4 # count [3:0] $end
$var parameter 32 $ WIDTH $end
$var reg 1 % clk $end
$var reg 1 & enable $end
$var reg 1 ' load $end
$var reg 4 ( load_val [3:0] $end
$var reg 1 ) rst_n $end
$var reg 1 * up_down $end
$var integer 32 + cov_down_seen [31:0] $end
$var integer 32 , cov_load_seen [31:0] $end
$var integer 32 - cov_overflow_seen [31:0] $end
$var integer 32 . cov_up_seen [31:0] $end
$var integer 32 / fail_count [31:0] $end
$var integer 32 0 pass_count [31:0] $end
$scope module dut $end
$var wire 1 % clk $end
$var wire 1 & enable $end
$var wire 1 ' load $end
$var wire 4 1 load_val [3:0] $end
$var wire 1 " overflow $end
$var wire 1 ) rst_n $end
$var wire 1 ! underflow $end
$var wire 1 * up_down $end
$var parameter 32 2 WIDTH $end
$var reg 4 3 count [3:0] $end
$upscope $end
$scope begin $unm_blk_17 $end
$var integer 32 4 cov_total [31:0] $end
$upscope $end
$upscope $end
$enddefinitions $end
$comment Show the parameter values. $end
$dumpall
b100 2
b100 $
$end
#0
$dumpvars
bx 4
b0 3
b0 1
b0 0
b0 /
b0 .
b0 -
b0 ,
b0 +
1*
0)
b0 (
0'
0&
0%
b0 #
0"
0!
$end
#5000
1%
#10000
0%
#15000
b1 #
b1 3
1&
1)
1%
#20000
0%
#25000
b10 #
b10 3
b1 .
1%
#30000
0%
#35000
b11 #
b11 3
1%
#40000
0%
#45000
b100 #
b100 3
1%
#50000
0%
#55000
b101 #
b101 3
1%
#60000
0%
#65000
b100 #
b100 3
b1 +
0*
b1 0
1&
1%
#70000
0%
#75000
b11 #
b11 3
1%
#80000
0%
#85000
b10 #
b10 3
1%
#90000
0%
#95000
b1010 #
b1010 3
b1010 (
b1010 1
1'
b10 0
0&
1%
#100000
0%
#105000
b1110 #
b1110 3
b1 ,
b1110 (
b1110 1
b11 0
1'
1%
#110000
0%
#115000
1"
b1111 #
b1111 3
1*
1&
0'
1%
#120000
0%
#125000
b0 #
b0 3
0"
b1 -
0)
0&
b100 0
1%
#130000
0%
#135000
b100 4
b101 0
1)
1%
