rtl/fifo.sv
// Simple Synchronous FIFO
// Depth: 8, Width: 8-bit
// Author: Sindhu Govindareddy Doddamane

module fifo #(
  parameter DEPTH = 8,
  parameter WIDTH = 8
)(
  input  logic             clk,
  input  logic             rst_n,
  input  logic             wr_en,
  input  logic             rd_en,
  input  logic [WIDTH-1:0] din,
  output logic [WIDTH-1:0] dout,
  output logic             full,
  output logic             empty
);

  logic [WIDTH-1:0] mem [0:DEPTH-1];
  logic [$clog2(DEPTH):0] wr_ptr, rd_ptr, count;

  // Write Logic
  always_ff @(posedge clk or negedge rst_n) begin
    if (!rst_n) wr_ptr <= 0;
    else if (wr_en && !full) begin
      mem[wr_ptr] <= din;
      wr_ptr <= wr_ptr + 1;
    end
  end

  // Read Logic
  always_ff @(posedge clk or negedge rst_n) begin
    if (!rst_n) rd_ptr <= 0;
    else if (rd_en && !empty) begin
      dout  <= mem[rd_ptr];
      rd_ptr <= rd_ptr + 1;
    end
  end

  // Count Logic
  always_ff @(posedge clk or negedge rst_n) begin
    if (!rst_n) count <= 0;
    else begin
      case ({wr_en & !full, rd_en & !empty})
        2'b10: count <= count + 1;
        2'b01: count <= count - 1;
        default: count <= count;
      endcase
    end
  end

  assign full  = (count == DEPTH);
  assign empty = (count == 0);

endmodule

tb/fifo_tb.sv
// FIFO Testbench
// Author: Sindhu Govindareddy Doddamane

`timescale 1ns/1ps

module fifo_tb;

  // Parameters
  parameter DEPTH = 8;
  parameter WIDTH = 8;

  // Signals
  logic             clk;
  logic             rst_n;
  logic             wr_en;
  logic             rd_en;
  logic [WIDTH-1:0] din;
  logic [WIDTH-1:0] dout;
  logic             full;
  logic             empty;

  // Instantiate DUT
  fifo #(.DEPTH(DEPTH), .WIDTH(WIDTH)) dut (
    .clk   (clk),
    .rst_n (rst_n),
    .wr_en (wr_en),
    .rd_en (rd_en),
    .din   (din),
    .dout  (dout),
    .full  (full),
    .empty (empty)
  );

  // Clock Generation: 10ns period
  initial clk = 0;
  always #5 clk = ~clk;

  // Coverage tracking (Icarus compatible)
  integer cov_full_seen  = 0;
  integer cov_empty_seen = 0;
  integer cov_wr_seen    = 0;
  integer cov_rd_seen    = 0;

  always @(posedge clk) begin
    if (full)  cov_full_seen  = 1;
    if (empty) cov_empty_seen = 1;
    if (wr_en) cov_wr_seen    = 1;
    if (rd_en) cov_rd_seen    = 1;
  end

  // Tasks
  task write_fifo(input logic [WIDTH-1:0] data);
    @(posedge clk);
    wr_en = 1;
    din   = data;
    @(posedge clk);
    wr_en = 0;
  endtask

  task read_fifo();
    @(posedge clk);
    rd_en = 1;
    @(posedge clk);
    rd_en = 0;
  endtask

  // Main Test
  integer pass_count = 0;
  integer fail_count = 0;

  initial begin
    // Init
    rst_n = 0; wr_en = 0; rd_en = 0; din = 0;
    repeat(2) @(posedge clk);
    rst_n = 1;

    // Test 1: Write until FULL
    $display("\n--- Test 1: Fill FIFO ---");
    repeat(DEPTH) begin
      write_fifo($random);
    end
    if (full) begin
      $display("PASS: FIFO is FULL as expected"); pass_count++;
    end else begin
      $display("FAIL: FIFO should be FULL"); fail_count++;
    end

    // Test 2: Write when FULL (should be ignored)
    $display("\n--- Test 2: Write when FULL ---");
    write_fifo(8'hFF);
    if (full) begin
      $display("PASS: Write ignored when FULL"); pass_count++;
    end else begin
      $display("FAIL: Overflow occurred"); fail_count++;
    end

    // Test 3: Read until EMPTY
    $display("\n--- Test 3: Drain FIFO ---");
    repeat(DEPTH) begin
      read_fifo();
    end
    if (empty) begin
      $display("PASS: FIFO is EMPTY as expected"); pass_count++;
    end else begin
      $display("FAIL: FIFO should be EMPTY"); fail_count++;
    end

    // Test 4: Read when EMPTY (should be ignored)
    $display("\n--- Test 4: Read when EMPTY ---");
    read_fifo();
    if (empty) begin
      $display("PASS: Read ignored when EMPTY"); pass_count++;
    end else begin
      $display("FAIL: Underflow occurred"); fail_count++;
    end

    // Test 5: Simultaneous Read/Write
    $display("\n--- Test 5: Simultaneous Read/Write ---");
    write_fifo(8'hAA);
    @(posedge clk);
    wr_en = 1; rd_en = 1; din = 8'hBB;
    @(posedge clk);
    wr_en = 0; rd_en = 0;
    $display("PASS: Simultaneous RD/WR completed"); pass_count++;

    // Summary
    $display("\n================================");
    $display("  TEST SUMMARY");
    $display("  PASSED : %0d", pass_count);
    $display("  FAILED : %0d", fail_count);
    $display("================================\n");

    // Coverage Report
    begin
  integer cov_total;
  cov_total = cov_full_seen + cov_empty_seen + cov_wr_seen + cov_rd_seen;
  $display("Functional Coverage: %0.2f%%", (cov_total / 4.0) * 100.0);
end

    $finish;
  end

  // Waveform dump
  initial begin
    $dumpfile("sim/fifo_tb.vcd");
    $dumpvars(0, fifo_tb);
  end

endmodule

sim/fifo_tb.vcd
$date
	Wed May  6 16:08:03 2026
$end
$version
	Icarus Verilog
$end
$timescale
	1ps
$end
$scope module fifo_tb $end
$var wire 1 ! full $end
$var wire 1 " empty $end
$var wire 8 # dout [7:0] $end
$var parameter 32 $ DEPTH $end
$var parameter 32 % WIDTH $end
$var reg 1 & clk $end
$var reg 8 ' din [7:0] $end
$var reg 1 ( rd_en $end
$var reg 1 ) rst_n $end
$var reg 1 * wr_en $end
$var integer 32 + cov_empty_seen [31:0] $end
$var integer 32 , cov_full_seen [31:0] $end
$var integer 32 - cov_rd_seen [31:0] $end
$var integer 32 . cov_wr_seen [31:0] $end
$var integer 32 / fail_count [31:0] $end
$var integer 32 0 pass_count [31:0] $end
$scope module dut $end
$var wire 1 & clk $end
$var wire 8 1 din [7:0] $end
$var wire 1 ( rd_en $end
$var wire 1 ) rst_n $end
$var wire 1 * wr_en $end
$var wire 1 ! full $end
$var wire 1 " empty $end
$var parameter 32 2 DEPTH $end
$var parameter 32 3 WIDTH $end
$var reg 4 4 count [3:0] $end
$var reg 8 5 dout [7:0] $end
$var reg 4 6 rd_ptr [3:0] $end
$var reg 4 7 wr_ptr [3:0] $end
$upscope $end
$scope begin $unm_blk_19 $end
$var integer 32 8 cov_total [31:0] $end
$upscope $end
$scope task read_fifo $end
$upscope $end
$scope task write_fifo $end
$var reg 8 9 data [7:0] $end
$upscope $end
$upscope $end
$enddefinitions $end
$comment Show the parameter values. $end
$dumpall
b1000 3
b1000 2
b1000 %
b1000 $
$end
#0
$dumpvars
bx 9
bx 8
b0 7
b0 6
bx 5
b0 4
b0 1
b0 0
b0 /
b0 .
b0 -
b0 ,
b0 +
0*
0)
0(
b0 '
0&
bx #
1"
0!
$end
#5000
b1 +
1&
#10000
0&
#15000
b100100 9
1)
1&
#20000
0&
#25000
0"
b1 4
b1 7
b1 .
b100100 '
b100100 1
1*
1&
#30000
0&
#35000
b10000001 9
0*
1&
#40000
0&
#45000
b10 4
b10 7
b10000001 '
b10000001 1
1*
1&
#50000
0&
#55000
b1001 9
0*
1&
#60000
0&
#65000
b11 4
b11 7
b1001 '
b1001 1
1*
1&
#70000
0&
#75000
b1100011 9
0*
1&
#80000
0&
#85000
b100 4
b100 7
b1100011 '
b1100011 1
1*
1&
#90000
0&
#95000
b1101 9
0*
1&
#100000
0&
#105000
b101 4
b101 7
b1101 '
b1101 1
1*
1&
#110000
0&
#115000
b10001101 9
0*
1&
#120000
0&
#125000
b110 4
b110 7
b10001101 '
b10001101 1
1*
1&
#130000
0&
#135000
b1100101 9
0*
1&
#140000
0&
#145000
b111 4
b111 7
b1100101 '
b1100101 1
1*
1&
#150000
0&
#155000
b10010 9
0*
1&
#160000
0&
#165000
1!
b1000 4
b1000 7
b10010 '
b10010 1
1*
1&
#170000
0&
#175000
b11111111 9
b1 0
0*
b1 ,
1&
#180000
0&
#185000
b11111111 '
b11111111 1
1*
1&
#190000
0&
#195000
b10 0
0*
1&
#200000
0&
#205000
0!
b111 4
b1 6
b100100 #
b100100 5
b1 -
1(
1&
#210000
0&
#215000
0(
1&
#220000
0&
#225000
b110 4
b10 6
b10000001 #
b10000001 5
1(
1&
#230000
0&
#235000
0(
1&
#240000
0&
#245000
b101 4
b11 6
b1001 #
b1001 5
1(
1&
#250000
0&
#255000
0(
1&
#260000
0&
#265000
b100 4
b100 6
b1100011 #
b1100011 5
1(
1&
#270000
0&
#275000
0(
1&
#280000
0&
#285000
b11 4
b101 6
b1101 #
b1101 5
1(
1&
#290000
0&
#295000
0(
1&
#300000
0&
#305000
b10 4
b110 6
b10001101 #
b10001101 5
1(
1&
#310000
0&
#315000
0(
1&
#320000
0&
#325000
b1 4
b111 6
b1100101 #
b1100101 5
1(
1&
#330000
0&
#335000
0(
1&
#340000
0&
#345000
1"
b0 4
b1000 6
b10010 #
b10010 5
1(
1&
#350000
0&
#355000
b11 0
0(
1&
#360000
0&
#365000
1(
1&
#370000
0&
#375000
b10101010 9
b100 0
0(
1&
#380000
0&
#385000
0"
b1 4
b1001 7
b10101010 '
b10101010 1
1*
1&
#390000
0&
#395000
0*
1&
#400000
0&
#405000
b1001 6
bx #
bx 5
b1010 7
b10111011 '
b10111011 1
1(
1*
1&
#410000
0&
#415000
b100 8
b101 0
0(
0*
1&
